ipysmrs/__init__.py
ipysmrs/common.py
ipysmrs/ipysmrs.py
ipysmrs-0.0.1.dist-info/LICENSE
ipysmrs-0.0.1.dist-info/METADATA
ipysmrs-0.0.1.dist-info/WHEEL
ipysmrs-0.0.1.dist-info/entry_points.txt
ipysmrs-0.0.1.dist-info/top_level.txt
ipysmrs-0.0.1.dist-info/RECORD
